android_sms_gateway/__init__.py
android_sms_gateway/ahttp.py
android_sms_gateway/client.py
android_sms_gateway/constants.py
android_sms_gateway/domain.py
android_sms_gateway/encryption.py
android_sms_gateway/enums.py
android_sms_gateway/errors.py
android_sms_gateway/http.py
android_sms_gateway-3.1.1.dist-info/licenses/LICENSE
android_sms_gateway-3.1.1.dist-info/METADATA
android_sms_gateway-3.1.1.dist-info/WHEEL
android_sms_gateway-3.1.1.dist-info/top_level.txt
android_sms_gateway-3.1.1.dist-info/RECORD
