Metadata-Version: 2.4
Name: android-sms-gateway
Version: 3.1.1
Summary: A client library for sending and managing SMS messages via the SMS Gateway for Android API
Author-email: Aleksandr Soloshenko <admin@sms-gate.app>
Maintainer-email: Aleksandr Soloshenko <support@sms-gate.app>
License: Apache-2.0
Project-URL: Homepage, https://sms-gate.app
Project-URL: Repository, https://github.com/android-sms-gateway/client-py
Keywords: android,sms,gateway
Classifier: Development Status :: 5 - Production/Stable
Classifier: Intended Audience :: Developers
Classifier: License :: OSI Approved :: Apache Software License
Classifier: Operating System :: OS Independent
Classifier: Programming Language :: Python :: 3
Classifier: Programming Language :: Python :: 3.9
Classifier: Programming Language :: Python :: 3.10
Classifier: Programming Language :: Python :: 3.11
Classifier: Programming Language :: Python :: 3.12
Classifier: Programming Language :: Python :: 3.13
Classifier: Topic :: Communications :: Telephony
Classifier: Topic :: Software Development :: Libraries :: Python Modules
Classifier: Typing :: Typed
Requires-Python: >=3.9
License-File: LICENSE
Provides-Extra: dev
Requires-Dist: setuptools; extra == "dev"
Requires-Dist: pytest; extra == "dev"
Requires-Dist: black; extra == "dev"
Requires-Dist: flake8; extra == "dev"
Requires-Dist: wheel; extra == "dev"
Provides-Extra: requests
Requires-Dist: requests; extra == "requests"
Provides-Extra: httpx
Requires-Dist: httpx; extra == "httpx"
Provides-Extra: aiohttp
Requires-Dist: aiohttp; extra == "aiohttp"
Provides-Extra: encryption
Requires-Dist: pycryptodome; extra == "encryption"
Dynamic: license-file
